{"inkVersion":21,"root":[["\n","ev",{"VAR?":"SKnight11Seen"},"!","/ev",[{"->":".^.b","c":true},{"b":["^ Fuhuhu... At last, my beauty shines even in the eyes of a dragon! ","#","^chara:knight ",{"->":"0.6"},null]}],"nop","/#","\n","ev",{"VAR?":"SKnight11Seen"},"/ev",[{"->":".^.b","c":true},{"b":["^ Fuhuhu... So, Dragon, what do you think of the beauty of Sir Edward the Magnificent? ","#","^chara:knight ",{"->":"0.13"},null]}],"nop","/#","\n","ev",{"VAR?":"SKnight11Seen"},"!","/ev",[{"->":".^.b","c":true},{"b":["^ ",{"->":"Encounter1"},{"->":"0.21"},null]}],"nop","\n","ev",{"VAR?":"SKnight11Seen"},"/ev",[{"->":".^.b","c":true},{"b":["^ ",{"->":"Encounter2"},{"->":"0.27"},null]}],"nop","\n",["done",{"#f":5,"#n":"g-0"}],null],"done",{"Encounter1":["^Another mad adventurer, boss! ","#","^chara:minion minion:in","/#","\n","ev",true,"/ev",{"VAR=":"SKnight11Seen","re":true},"^Fuhuhu... I understand that my beauty is almost unreal, but to call me mad... ","#","^chara:knight","/#","\n","^I'm not interested in such things, hero, but I hope you have more than just looks to impress me in battle. ","#","^chara:dragon","/#","\n","^But of course, Dragon, you'll soon realize that my beauty goes beyond mere decoration! ","#","^chara:knight","/#","\n","^Perfect, let's fight then! ","#","^chara:dragon ","/#","#","^minion:out","/#","\n","end",{"#f":1}],"Encounter2":["^I must admit, knight, I'm surprised; we've had quite a good battle! ","#","^chara:dragon","/#","\n","^Fuhuhu... Naturally! After all, I am exceptional. ","#","^chara:knight","/#","\n","^Just this time, avoid bursting into song in the middle of the fight! ","#","^chara:dragon","/#","\n","^What? But... ","#","^chara:knight","/#","\n","^We're not in a musical, Edward. Stop dancing and singing in my dungeon! ","#","^chara:dragon","/#","\n","end",{"#f":1}],"global decl":["ev",false,{"VAR=":"RknightSeen"},true,{"VAR=":"SKnight2SeenTwice"},false,{"VAR=":"SMage1SeenTwice"},false,{"VAR=":"SKnight1Seen"},false,{"VAR=":"SKnight2Seen"},false,{"VAR=":"SKnight3Seen"},false,{"VAR=":"SKnight4Seen"},false,{"VAR=":"SKnight5Seen"},false,{"VAR=":"SKnight6Seen"},false,{"VAR=":"SKnight7Seen"},false,{"VAR=":"SKnight8Seen"},false,{"VAR=":"SKnight9Seen"},false,{"VAR=":"SKnight10Seen"},false,{"VAR=":"SKnight11Seen"},false,{"VAR=":"SKnight12Seen"},false,{"VAR=":"SKnight13Seen"},false,{"VAR=":"SKnight14Seen"},false,{"VAR=":"SKnight15Seen"},false,{"VAR=":"SKnight16Seen"},false,{"VAR=":"SKnight17Seen"},false,{"VAR=":"SBarbarian1Seen"},false,{"VAR=":"SBarbarian2Seen"},false,{"VAR=":"SBarbarian3Seen"},false,{"VAR=":"SBarbarian4Seen"},false,{"VAR=":"SBarbarian5Seen"},false,{"VAR=":"SArcher1Seen"},false,{"VAR=":"SArcher2Seen"},false,{"VAR=":"SArcher3Seen"},false,{"VAR=":"SArcher4Seen"},false,{"VAR=":"SMage1Seen"},false,{"VAR=":"SMage2Seen"},false,{"VAR=":"SMage3Seen"},"/ev","end",null],"#f":1}],"listDefs":{}}